topicnet/__init__.py
topicnet/cooking_machine/__init__.py
topicnet/cooking_machine/config_parser.py
topicnet/cooking_machine/dataset.py
topicnet/cooking_machine/dataset_cooc.py
topicnet/cooking_machine/experiment.py
topicnet/cooking_machine/model_constructor.py
topicnet/cooking_machine/model_tracking.py
topicnet/cooking_machine/pretty_output.py
topicnet/cooking_machine/rel_toolbox_lite.py
topicnet/cooking_machine/routine.py
topicnet/cooking_machine/cubes/__init__.py
topicnet/cooking_machine/cubes/base_cube.py
topicnet/cooking_machine/cubes/controller_cube.py
topicnet/cooking_machine/cubes/cube_creator.py
topicnet/cooking_machine/cubes/greedy_strategy.py
topicnet/cooking_machine/cubes/perplexity_strategy.py
topicnet/cooking_machine/cubes/regularizer_cube.py
topicnet/cooking_machine/cubes/strategy.py
topicnet/cooking_machine/models/__init__.py
topicnet/cooking_machine/models/base_model.py
topicnet/cooking_machine/models/base_regularizer.py
topicnet/cooking_machine/models/base_score.py
topicnet/cooking_machine/models/blei_lafferty_score.py
topicnet/cooking_machine/models/dummy_topic_model.py
topicnet/cooking_machine/models/example_score.py
topicnet/cooking_machine/models/frozen_score.py
topicnet/cooking_machine/models/intratext_coherence_score.py
topicnet/cooking_machine/models/scores.py
topicnet/cooking_machine/models/scores_wrapper.py
topicnet/cooking_machine/models/semantic_radius_score.py
topicnet/cooking_machine/models/thetaless_regularizer.py
topicnet/cooking_machine/models/topic_model.py
topicnet/cooking_machine/models/topic_prior_regularizer.py
topicnet/cooking_machine/recipes/__init__.py
topicnet/cooking_machine/recipes/artm_baseline_pipeline.py
topicnet/cooking_machine/recipes/exploratory_search_pipeline.py
topicnet/cooking_machine/recipes/intratext_coherence_pipeline.py
topicnet/cooking_machine/recipes/multimodal_exploratory_search_pipeline.py
topicnet/cooking_machine/recipes/recipe_wrapper.py
topicnet/cooking_machine/recipes/wntm.py
topicnet-0.9.0.dist-info/LICENSE.txt
topicnet-0.9.0.dist-info/METADATA
topicnet-0.9.0.dist-info/WHEEL
topicnet-0.9.0.dist-info/top_level.txt
topicnet-0.9.0.dist-info/RECORD
