Metadata-Version: 2.1
Name: topicnet
Version: 0.9.0
Summary: TopicNet is a module for topic modelling using ARTM algorithm
Home-page: https://github.com/machine-intelligence-laboratory/TopicNet
Download-URL: https://github.com/machine-intelligence-laboratory/TopicNet/archive/v0.9.0.tar.gz
Author: Machine Intelligence Laboratory
Author-email: alex.goncharov@phystech.edu
License: MIT
Keywords: ARTM,topic modeling,regularization,multimodal learning,document vector representation
Classifier: Development Status :: 4 - Beta
Classifier: Intended Audience :: Developers
Classifier: Topic :: Scientific/Engineering :: Artificial Intelligence
Classifier: Topic :: Scientific/Engineering :: Information Analysis
Classifier: License :: OSI Approved :: MIT License
Classifier: Programming Language :: Python :: 3.8
License-File: LICENSE.txt
Requires-Dist: bigartm >=0.9.2
Requires-Dist: colorlover ==0.3.0
Requires-Dist: dask[dataframe] ==2023.5.0
Requires-Dist: dill ==0.3.8
Requires-Dist: ipython ==8.12.3
Requires-Dist: jinja2 ==3.1.4
Requires-Dist: numba ==0.58.1
Requires-Dist: numexpr ==2.8.6
Requires-Dist: numpy ==1.24.4
Requires-Dist: pandas ==2.0.3
Requires-Dist: plotly ==5.20.0
Requires-Dist: protobuf ==3.20.3
Requires-Dist: pytest ==8.1.1
Requires-Dist: scikit-learn ==1.3.2
Requires-Dist: scipy ==1.10.1
Requires-Dist: six ==1.16.0
Requires-Dist: strictyaml ==1.7.3
Requires-Dist: toolz ==0.12.1
Requires-Dist: tqdm ==4.66.3
